odoo/addons/stock_location_position/README.rst
odoo/addons/stock_location_position/__init__.py
odoo/addons/stock_location_position/__manifest__.py
odoo/addons/stock_location_position/i18n/es.po
odoo/addons/stock_location_position/i18n/fr.po
odoo/addons/stock_location_position/i18n/it.po
odoo/addons/stock_location_position/i18n/stock_location_position.pot
odoo/addons/stock_location_position/models/__init__.py
odoo/addons/stock_location_position/models/stock_location.py
odoo/addons/stock_location_position/readme/CONTRIBUTORS.md
odoo/addons/stock_location_position/readme/CREDITS.md
odoo/addons/stock_location_position/readme/DESCRIPTION.md
odoo/addons/stock_location_position/static/description/icon.png
odoo/addons/stock_location_position/static/description/index.html
odoo/addons/stock_location_position/tests/__init__.py
odoo/addons/stock_location_position/tests/test_stock_location_position.py
odoo/addons/stock_location_position/views/stock_location.xml
odoo_addon_stock_location_position-18.0.1.0.0.5.dist-info/METADATA
odoo_addon_stock_location_position-18.0.1.0.0.5.dist-info/WHEEL
odoo_addon_stock_location_position-18.0.1.0.0.5.dist-info/top_level.txt
odoo_addon_stock_location_position-18.0.1.0.0.5.dist-info/RECORD
