Metadata-Version: 2.1
Name: odoo-addon-stock_location_position
Version: 18.0.1.0.0.5
Requires-Python: >=3.10
Requires-Dist: odoo==18.0.*
Summary: Add coordinate attributes on stock location.
Home-page: https://github.com/OCA/stock-logistics-warehouse
License: AGPL-3
Author: BCIM, Okia, Camptocamp, Odoo Community Association (OCA)
Author-email: support@odoo-community.org
Classifier: Programming Language :: Python
Classifier: Framework :: Odoo
Classifier: Framework :: Odoo :: 18.0
Classifier: License :: OSI Approved :: GNU Affero General Public License v3
Classifier: Development Status :: 5 - Production/Stable
